MANIFEST.in
README.md
build.py
requirements.txt
setup.py
sockets_io.egg-info/PKG-INFO
sockets_io.egg-info/SOURCES.txt
sockets_io.egg-info/dependency_links.txt
sockets_io.egg-info/requires.txt
sockets_io.egg-info/top_level.txt
socketsio/__init__.py
socketsio/client.py
socketsio/protocols.py
socketsio/queue.py
socketsio/server.py
socketsio/sockets.py
socketsio/utils.py
socketsio/pubsub/__init__.py
socketsio/pubsub/data.py
socketsio/pubsub/store.py
socketsio/pubsub/streamer.py
socketsio/pubsub/subscriber.py