Metadata-Version: 2.1
Name: sockets-io
Version: 0.0.0
Summary: This module provides a wrapper for the built-in socket module in python. The program provides server and. client classes, with the communication methods.
Home-page: https://github.com/Shahaf-F-S/socketsio
Author: Shahaf Frank-Shapir
Author-email: shahaffrs@gmail.com
License: MIT
Classifier: Intended Audience :: Developers
Classifier: License :: OSI Approved :: MIT License
Classifier: Programming Language :: Python
Classifier: Programming Language :: Python :: 3.11
Classifier: Programming Language :: Python :: 3.12
Classifier: Operating System :: OS Independent
Requires-Dist: looperation
Provides-Extra: dev
